put/__init__.py
put/fileutils.py
put/hashutils.py
put/jsonutils.py
put/strutils.py
put-0.0.7.dist-info/LICENSE
put-0.0.7.dist-info/METADATA
put-0.0.7.dist-info/WHEEL
put-0.0.7.dist-info/top_level.txt
put-0.0.7.dist-info/RECORD
