Metadata-Version: 2.1
Name: put
Version: 0.0.7
Summary: collection of wonderful python utilities and tools that can make your life easier
Home-page: https://github.com/an63/put
Author: Angel Analoosen
Author-email: an9an63@gmail.com
License: UNKNOWN
Project-URL: Documentation, https://github.com/an63/put/wiki
Platform: any
Classifier: Development Status :: 1 - Planning
Classifier: Programming Language :: Python
Classifier: Intended Audience :: Developers
Classifier: Natural Language :: English
Classifier: License :: OSI Approved :: MIT License
Classifier: Programming Language :: Python
Classifier: Programming Language :: Python :: 3
Classifier: Programming Language :: Python :: 3.5
Classifier: Programming Language :: Python :: 3.6
Classifier: Programming Language :: Python :: 3.7
Classifier: Programming Language :: Python :: 3.8
Classifier: Topic :: Utilities
Provides-Extra: testing
